AUTHORS
ChangeLog
README.md
requirements.txt
setup.cfg
setup.py
dockerdevice/__init__.py
dockerdevice/gpu.py
dockerdevice/main.py
dockerdevice/version.py
dockerdevice.egg-info/PKG-INFO
dockerdevice.egg-info/SOURCES.txt
dockerdevice.egg-info/dependency_links.txt
dockerdevice.egg-info/entry_points.txt
dockerdevice.egg-info/not-zip-safe
dockerdevice.egg-info/pbr.json
dockerdevice.egg-info/requires.txt
dockerdevice.egg-info/top_level.txt
etc/dockerdevice/Dockerfile
etc/dockerdevice/docker-compose.yml