Metadata-Version: 1.0
Name: dockerdevice
Version: 2017.10.25.dev15
Summary: dockerdevice
Home-page: https://github.com/bhanum2/dockerdevice
Author: bhanum2
Author-email: no-reply@gmail.com
License: UNKNOWN
Platform: UNKNOWN
